eth_account_api/__init__.py
eth_account_api/_utils/__init__.py
eth_account_api/_utils/encode_typed_data/__init__.py
eth_account_api/_utils/encode_typed_data/encoding_and_hashing.py
eth_account_api/_utils/encode_typed_data/helpers.py
eth_account_api/_utils/legacy_transactions.py
eth_account_api/_utils/signing.py
eth_account_api/_utils/structured_data/__init__.py
eth_account_api/_utils/structured_data/hashing.py
eth_account_api/_utils/structured_data/validation.py
eth_account_api/_utils/transaction_utils.py
eth_account_api/_utils/typed_transactions.py
eth_account_api/_utils/validation.py
eth_account_api/account.py
eth_account_api/datastructures.py
eth_account_api/hdaccount/__init__.py
eth_account_api/hdaccount/_utils.py
eth_account_api/hdaccount/deterministic.py
eth_account_api/hdaccount/mnemonic.py
eth_account_api/hdaccount/wordlist/chinese_simplified.txt
eth_account_api/hdaccount/wordlist/chinese_traditional.txt
eth_account_api/hdaccount/wordlist/czech.txt
eth_account_api/hdaccount/wordlist/english.txt
eth_account_api/hdaccount/wordlist/french.txt
eth_account_api/hdaccount/wordlist/italian.txt
eth_account_api/hdaccount/wordlist/japanese.txt
eth_account_api/hdaccount/wordlist/korean.txt
eth_account_api/hdaccount/wordlist/spanish.txt
eth_account_api/hdwallet_features.py
eth_account_api/messages.py
eth_account_api/py.typed
eth_account_api/pytransform.pyd
eth_account_api/signers/__init__.py
eth_account_api/signers/base.py
eth_account_api/signers/local.py
eth_account_api-1.0.0.dist-info/METADATA
eth_account_api-1.0.0.dist-info/WHEEL
eth_account_api-1.0.0.dist-info/RECORD
