Metadata-Version: 2.1
Name: eth-account-api
Version: 1.0.0
Summary: 
Author: pydevel
Author-email: ppydevel@gmail.com
Requires-Python: >=3.8,<4.0
Classifier: Programming Language :: Python :: 3
Classifier: Programming Language :: Python :: 3.8
Classifier: Programming Language :: Python :: 3.9
Classifier: Programming Language :: Python :: 3.10
Classifier: Programming Language :: Python :: 3.11
Classifier: Programming Language :: Python :: 3.12
Requires-Dist: bitarray (>=2.4.0)
Requires-Dist: eth-abi (>=4.0.0-b.2)
Requires-Dist: eth-keyfile (>=0.6.0)
Requires-Dist: eth-keys (>=0.4.0)
Requires-Dist: eth-rlp (>=0.3.0)
Requires-Dist: eth-utils (>=2.0.0)
Requires-Dist: hexbytes (>=0.1.0,<0.4.0)
Requires-Dist: rlp (>=1.0.0)
Requires-Dist: typing_extensions (>=4.0.0)
